test_module_gannu.py
test_module_gannu-1.0.0.dist-info/METADATA
test_module_gannu-1.0.0.dist-info/WHEEL
test_module_gannu-1.0.0.dist-info/top_level.txt
test_module_gannu-1.0.0.dist-info/RECORD
