Metadata-Version: 2.1
Name: test-module-gannu
Version: 1.0.0
Summary: THis is testmodule that I want to upload in pypi
Home-page: https://sampleganesh.com/test_module
Author: ganesh
Author-email: ganeshperi14@gmal.com
License: UNKNOWN
Platform: UNKNOWN
